aliyun_python_sdk_cf-2.0.0.1.dist-info/DESCRIPTION.rst
aliyun_python_sdk_cf-2.0.0.1.dist-info/METADATA
aliyun_python_sdk_cf-2.0.0.1.dist-info/metadata.json
aliyun_python_sdk_cf-2.0.0.1.dist-info/pbr.json
aliyun_python_sdk_cf-2.0.0.1.dist-info/RECORD
aliyun_python_sdk_cf-2.0.0.1.dist-info/top_level.txt
aliyun_python_sdk_cf-2.0.0.1.dist-info/WHEEL
aliyunsdkcf/__init__.py
aliyunsdkcf/request/__init__.py
aliyunsdkcf/request/v20151127/__init__.py
aliyunsdkcf/request/v20151127/AuthenticateRequest.py
aliyunsdkcf/request/v20151127/CfAccountFeedbackRequest.py
aliyunsdkcf/request/v20151127/CfAccountQueryRequest.py
aliyunsdkcf/request/v20151127/QuerySimpleRequest.py
