Metadata-Version: 2.0
Name: aliyun-python-sdk-cf
Version: 2.0.0.1
Summary: The cf module of Aliyun Python sdk.
Home-page: http://develop.aliyun.com/sdk/python
Author: Aliyun
Author-email: aliyun-developers-efficiency@list.alibaba-inc.com
License: Apache
Keywords: aliyun,sdk,cf
Platform: any
Classifier: Development Status :: 4 - Beta
Classifier: Intended Audience :: Developers
Classifier: License :: OSI Approved :: Apache Software License
Classifier: Programming Language :: Python
Classifier: Programming Language :: Python :: 2.6
Classifier: Programming Language :: Python :: 2.7
Classifier: Programming Language :: Python :: 3
Classifier: Programming Language :: Python :: 3.3
Classifier: Topic :: Software Development
Requires-Dist: aliyun-python-sdk-core-patch-cf (>=2.0.2)
